{
    "key": "group_630b7825ea73e",
    "title": "Character Profile",
    "fields": [
        {
            "key": "field_630b7838ee962",
            "label": "Artist",
            "name": "artist",
            "aria-label": "",
            "type": "relationship",
            "instructions": "",
            "required": 0,
            "conditional_logic": 0,
            "wrapper": {
                "width": "",
                "class": "",
                "id": ""
            },
            "post_type": [
                "staff"
            ],
            "taxonomy": "",
            "filters": [
                "search",
                "post_type",
                "taxonomy"
            ],
            "elements": "",
            "min": "",
            "max": "",
            "return_format": "object",
            "bidirectional_target": []
        },
        {
            "key": "field_630b7855ee963",
            "label": "NPC",
            "name": "npc",
            "aria-label": "",
            "type": "true_false",
            "instructions": "",
            "required": 0,
            "conditional_logic": 0,
            "wrapper": {
                "width": "",
                "class": "",
                "id": ""
            },
            "message": "",
            "default_value": 1,
            "ui": 1,
            "ui_on_text": "PC",
            "ui_off_text": "NPC"
        },
        {
            "key": "field_630b788cee965",
            "label": "Character Information",
            "name": "character_information",
            "aria-label": "",
            "type": "repeater",
            "instructions": "",
            "required": 0,
            "conditional_logic": 0,
            "wrapper": {
                "width": "",
                "class": "",
                "id": ""
            },
            "collapsed": "",
            "min": 0,
            "max": 0,
            "layout": "table",
            "button_label": "Add Row",
            "sub_fields": [
                {
                    "key": "field_630b789cee966",
                    "label": "Heading",
                    "name": "heading",
                    "aria-label": "",
                    "type": "text",
                    "instructions": "",
                    "required": 0,
                    "conditional_logic": 0,
                    "wrapper": {
                        "width": "",
                        "class": "",
                        "id": ""
                    },
                    "default_value": "",
                    "placeholder": "",
                    "prepend": "",
                    "append": "",
                    "maxlength": "",
                    "parent_repeater": "field_630b788cee965"
                },
                {
                    "key": "field_630b78a3ee967",
                    "label": "Details",
                    "name": "details",
                    "aria-label": "",
                    "type": "text",
                    "instructions": "",
                    "required": 0,
                    "conditional_logic": 0,
                    "wrapper": {
                        "width": "",
                        "class": "",
                        "id": ""
                    },
                    "default_value": "",
                    "placeholder": "",
                    "prepend": "",
                    "append": "",
                    "maxlength": "",
                    "parent_repeater": "field_630b788cee965"
                }
            ],
            "rows_per_page": 20
        },
        {
            "key": "field_630b78b3ee968",
            "label": "Backstory",
            "name": "backstory",
            "aria-label": "",
            "type": "wysiwyg",
            "instructions": "",
            "required": 0,
            "conditional_logic": 0,
            "wrapper": {
                "width": "",
                "class": "",
                "id": ""
            },
            "default_value": "",
            "tabs": "all",
            "toolbar": "full",
            "media_upload": 1,
            "delay": 0
        },
        {
            "key": "field_630b78baee969",
            "label": "Adventures",
            "name": "adventures",
            "aria-label": "",
            "type": "wysiwyg",
            "instructions": "",
            "required": 0,
            "conditional_logic": 0,
            "wrapper": {
                "width": "",
                "class": "",
                "id": ""
            },
            "default_value": "",
            "tabs": "all",
            "toolbar": "full",
            "media_upload": 1,
            "delay": 0
        }
    ],
    "location": [
        [
            {
                "param": "block",
                "operator": "==",
                "value": "fbf\/rpg-character-profile"
            }
        ]
    ],
    "menu_order": 0,
    "position": "normal",
    "style": "default",
    "label_placement": "top",
    "instruction_placement": "label",
    "hide_on_screen": "",
    "active": true,
    "description": "",
    "show_in_rest": 0,
    "modified": 1708587981
}
